etfscan/__init__.py
etfscan/create_etf.py
etfscan/etf.py
etfscan-24.9.30.dist-info/LICENSE
etfscan-24.9.30.dist-info/METADATA
etfscan-24.9.30.dist-info/WHEEL
etfscan-24.9.30.dist-info/entry_points.txt
etfscan-24.9.30.dist-info/top_level.txt
etfscan-24.9.30.dist-info/RECORD
