Metadata-Version: 2.1
Name: etfscan
Version: 24.9.30
Summary: Library and tool for handling ETF files.
Home-page: https://gitlab.esrf.fr/night_rail/applications/tools/etfscan
Author: Alessandro Mirone
Author-email: alessandro@example.com
License: MIT
Platform: UNKNOWN
Classifier: Programming Language :: Python :: 3
Classifier: License :: OSI Approved :: MIT License
Classifier: Operating System :: OS Independent
Classifier: Development Status :: 4 - Beta
Classifier: Intended Audience :: Developers
Requires-Python: >=3.6
License-File: LICENSE
Requires-Dist: wheel
Requires-Dist: nxtomomill
Requires-Dist: scipy
Requires-Dist: numpy
Requires-Dist: namedlist
